{
  "category": "motor",
  "lastUpdated": "2026-04-03",
  "disclaimer": "Data collected from publicly available sources for educational and informational purposes only. Premium figures are illustrative and sourced from public insurer calculators/brochures. Actual premiums may vary. Please verify all details with the insurer directly before making any decision.",
  "products": [
    {
      "id": "hdfc-ergo-motor",
      "insurerName": "HDFC ERGO General Insurance Co. Ltd.",
      "insurerSlug": "hdfc-ergo",
      "productName": "HDFC ERGO Motor Insurance",
      "category": "motor",
      "subCategory": "comprehensive",
      "eligibility": {
        "minAge": 18,
        "maxAge": 65,
        "renewableUpTo": "lifetime"
      },
      "sumInsured": {
        "min": null,
        "max": null,
        "options": []
      },
      "premiumRange": {
        "illustrativeMin": 5000,
        "illustrativeMax": 25000,
        "assumptions": "Comprehensive, mid-size sedan, metro city. Indicative only.",
        "isVerified": false
      },
      "keyInclusions": [
        "Own damage cover",
        "Third-party liability",
        "Personal accident cover",
        "Cashless repairs",
        "Roadside assistance"
      ],
      "keyExclusions": [
        "Pre-existing diseases during waiting period",
        "Cosmetic surgery (unless medically necessary)",
        "Self-inflicted injuries"
      ],
      "claimSettlement": {
        "ratio": 99,
        "year": "FY2023-24",
        "source": "IRDAI / Insurer website"
      },
      "riders": [],
      "policyTenure": {
        "min": 1,
        "max": 1,
        "options": [
          1
        ]
      },
      "renewability": "Lifelong",
      "specialFeatures": [
        "12,200+ Cashless Garages",
        "99% CSR",
        "Digital Claims",
        "Real-Time Policy Tracking"
      ],
      "sourceUrl": "https://www.hdfcergo.com/motor-insurance",
      "sourceType": "official-website",
      "lastVerified": "2026-04-03",
      "confidenceScore": "high",
      "notes": "",
      "countryCode": "in"
    },
    {
      "id": "bajaj-allianz-motor",
      "insurerName": "Bajaj Allianz General Insurance Co. Ltd.",
      "insurerSlug": "bajaj-allianz",
      "productName": "Bajaj Allianz Motor Insurance",
      "category": "motor",
      "subCategory": "comprehensive",
      "eligibility": {
        "minAge": 18,
        "maxAge": 65,
        "renewableUpTo": "lifetime"
      },
      "sumInsured": {
        "min": null,
        "max": null,
        "options": []
      },
      "premiumRange": {
        "illustrativeMin": 4500,
        "illustrativeMax": 22000,
        "assumptions": "Comprehensive, mid-size sedan, metro city. Indicative only.",
        "isVerified": false
      },
      "keyInclusions": [
        "Own damage cover",
        "Third-party liability",
        "Personal accident cover",
        "Cashless repairs"
      ],
      "keyExclusions": [
        "Pre-existing diseases during waiting period",
        "Cosmetic surgery (unless medically necessary)",
        "Self-inflicted injuries"
      ],
      "claimSettlement": {
        "ratio": 98.5,
        "year": "FY2023-24",
        "source": "IRDAI / Insurer website"
      },
      "riders": [],
      "policyTenure": {
        "min": 1,
        "max": 1,
        "options": [
          1
        ]
      },
      "renewability": "Lifelong",
      "specialFeatures": [
        "7,200+ Cashless Garages",
        "Largest Private Network",
        "Mobile App",
        "98.5% CSR"
      ],
      "sourceUrl": "https://www.bajajallianz.com/motor-insurance.html",
      "sourceType": "official-website",
      "lastVerified": "2026-04-03",
      "confidenceScore": "high",
      "notes": "",
      "countryCode": "in"
    },
    {
      "id": "icici-lombard-motor",
      "insurerName": "ICICI Lombard General Insurance Co. Ltd.",
      "insurerSlug": "icici-lombard",
      "productName": "ICICI Lombard Motor Insurance",
      "category": "motor",
      "subCategory": "comprehensive",
      "eligibility": {
        "minAge": 18,
        "maxAge": 65,
        "renewableUpTo": "lifetime"
      },
      "sumInsured": {
        "min": null,
        "max": null,
        "options": []
      },
      "premiumRange": {
        "illustrativeMin": 5000,
        "illustrativeMax": 23000,
        "assumptions": "Comprehensive, mid-size sedan, metro city. Indicative only.",
        "isVerified": false
      },
      "keyInclusions": [
        "Own damage cover",
        "Third-party liability",
        "Personal accident cover",
        "Cashless repairs"
      ],
      "keyExclusions": [
        "Pre-existing diseases during waiting period",
        "Cosmetic surgery (unless medically necessary)",
        "Self-inflicted injuries"
      ],
      "claimSettlement": {
        "ratio": 96.75,
        "year": "FY2023-24",
        "source": "IRDAI / Insurer website"
      },
      "riders": [],
      "policyTenure": {
        "min": 1,
        "max": 1,
        "options": [
          1
        ]
      },
      "renewability": "Lifelong",
      "specialFeatures": [
        "5,900+ Cashless Garages",
        "Established Brand",
        "Quick Claim Settlement"
      ],
      "sourceUrl": "https://www.icicilombard.com/motor-insurance",
      "sourceType": "official-website",
      "lastVerified": "2026-04-03",
      "confidenceScore": "high",
      "notes": "",
      "countryCode": "in"
    },
    {
      "id": "digit-motor",
      "insurerName": "Go Digit General Insurance Ltd.",
      "insurerSlug": "digit",
      "productName": "Digit Motor Insurance",
      "category": "motor",
      "subCategory": "comprehensive",
      "eligibility": {
        "minAge": 18,
        "maxAge": 65,
        "renewableUpTo": "lifetime"
      },
      "sumInsured": {
        "min": null,
        "max": null,
        "options": []
      },
      "premiumRange": {
        "illustrativeMin": 3500,
        "illustrativeMax": 18000,
        "assumptions": "Comprehensive, mid-size sedan. Indicative only.",
        "isVerified": false
      },
      "keyInclusions": [
        "Own damage cover",
        "Third-party liability",
        "Personal accident cover"
      ],
      "keyExclusions": [
        "Pre-existing diseases during waiting period",
        "Cosmetic surgery (unless medically necessary)",
        "Self-inflicted injuries"
      ],
      "claimSettlement": {
        "ratio": 84,
        "year": "FY2023-24",
        "source": "IRDAI / Insurer website"
      },
      "riders": [],
      "policyTenure": {
        "min": 1,
        "max": 1,
        "options": [
          1
        ]
      },
      "renewability": "Lifelong",
      "specialFeatures": [
        "Digital-First",
        "Paperless Claims",
        "Affordable Premiums"
      ],
      "sourceUrl": "https://www.godigit.com/motor-insurance",
      "sourceType": "official-website",
      "lastVerified": "2026-04-03",
      "confidenceScore": "medium",
      "notes": "",
      "countryCode": "in"
    },
    {
      "id": "acko-car-insurance",
      "insurerName": "Acko General Insurance Ltd.",
      "insurerSlug": "acko",
      "productName": "Acko Car Insurance",
      "category": "motor",
      "subCategory": "comprehensive",
      "eligibility": {
        "minAge": 18,
        "maxAge": 65,
        "renewableUpTo": "lifetime"
      },
      "sumInsured": {
        "min": null,
        "max": null,
        "options": []
      },
      "premiumRange": {
        "illustrativeMin": 3000,
        "illustrativeMax": 15000,
        "assumptions": "Comprehensive, mid-size sedan. Indicative only.",
        "isVerified": false
      },
      "keyInclusions": [
        "Own damage cover",
        "Third-party liability",
        "Personal accident cover"
      ],
      "keyExclusions": [
        "Pre-existing diseases during waiting period",
        "Cosmetic surgery (unless medically necessary)",
        "Self-inflicted injuries"
      ],
      "claimSettlement": {
        "ratio": 80,
        "year": "FY2023-24",
        "source": "IRDAI / Insurer website"
      },
      "riders": [],
      "policyTenure": {
        "min": 1,
        "max": 1,
        "options": [
          1
        ]
      },
      "renewability": "Lifelong",
      "specialFeatures": [
        "Zero-Commission Model",
        "App-Based Claims",
        "4,000+ Garages",
        "Lowest Premiums"
      ],
      "sourceUrl": "https://www.acko.com/car-insurance",
      "sourceType": "official-website",
      "lastVerified": "2026-04-03",
      "confidenceScore": "medium",
      "notes": "",
      "countryCode": "in"
    },
    {
      "id": "tata-aig-motor",
      "insurerName": "Tata AIG General Insurance Co. Ltd.",
      "insurerSlug": "tata-aig",
      "productName": "Tata AIG Motor Insurance",
      "category": "motor",
      "subCategory": "comprehensive",
      "eligibility": {
        "minAge": 18,
        "maxAge": 65,
        "renewableUpTo": "lifetime"
      },
      "sumInsured": {
        "min": null,
        "max": null,
        "options": []
      },
      "premiumRange": {
        "illustrativeMin": 4500,
        "illustrativeMax": 20000,
        "assumptions": "Comprehensive, mid-size sedan. Indicative only.",
        "isVerified": false
      },
      "keyInclusions": [
        "Own damage cover",
        "Third-party liability",
        "Personal accident cover",
        "Roadside assistance"
      ],
      "keyExclusions": [
        "Pre-existing diseases during waiting period",
        "Cosmetic surgery (unless medically necessary)",
        "Self-inflicted injuries"
      ],
      "claimSettlement": {
        "ratio": 77,
        "year": "FY2023-24",
        "source": "IRDAI / Insurer website"
      },
      "riders": [],
      "policyTenure": {
        "min": 1,
        "max": 1,
        "options": [
          1
        ]
      },
      "renewability": "Lifelong",
      "specialFeatures": [
        "7,500+ Garages",
        "Restoration Benefit",
        "Roadside Assistance"
      ],
      "sourceUrl": "https://www.tataaig.com/motor-insurance",
      "sourceType": "official-website",
      "lastVerified": "2026-04-03",
      "confidenceScore": "medium",
      "notes": "",
      "countryCode": "in"
    },
    {
      "id": "new-india-motor",
      "insurerName": "The New India Assurance Co. Ltd.",
      "insurerSlug": "new-india-assurance",
      "productName": "New India Motor Insurance",
      "category": "motor",
      "subCategory": "comprehensive",
      "eligibility": {
        "minAge": 18,
        "maxAge": 65,
        "renewableUpTo": "lifetime"
      },
      "sumInsured": {
        "min": null,
        "max": null,
        "options": []
      },
      "premiumRange": {
        "illustrativeMin": 4000,
        "illustrativeMax": 18000,
        "assumptions": "Comprehensive, mid-size sedan. Indicative only.",
        "isVerified": false
      },
      "keyInclusions": [
        "Own damage cover",
        "Third-party liability",
        "Personal accident cover"
      ],
      "keyExclusions": [
        "Pre-existing diseases during waiting period",
        "Cosmetic surgery (unless medically necessary)",
        "Self-inflicted injuries"
      ],
      "claimSettlement": {
        "ratio": 91,
        "year": "FY2023-24",
        "source": "IRDAI / Insurer website"
      },
      "riders": [],
      "policyTenure": {
        "min": 1,
        "max": 1,
        "options": [
          1
        ]
      },
      "renewability": "Lifelong",
      "specialFeatures": [
        "Government-Backed",
        "91% CSR",
        "8,000+ Garages",
        "Oldest General Insurer"
      ],
      "sourceUrl": "https://www.newindia.co.in",
      "sourceType": "official-website",
      "lastVerified": "2026-04-03",
      "confidenceScore": "medium",
      "notes": "",
      "countryCode": "in"
    }
  ]
}